Workbook

Sheet Per-Transaction Costs
A1: SPLITT. — PER-TRANSACTION COST MODEL
A2: What does each split actually cost us?
A4: TRANSACTION ASSUMPTIONS
A5: Average transaction amount | B5: 75 | D5: Source: Typical consumer purchase size
A6: Average number of cards in split | B6: 2.5 | D6: Source: Assumption — most users split across 2-3 cards
A7: Average amount per secondary card charge | B7: =B5/B6 -> 30 | D7: Total / Cards in split
A9: STRIPE FEES — Secondary Card Charges | D9: Source: stripe.com/pricing
A10: Stripe % fee per charge | B10: 0.029
A11: Stripe fixed fee per charge | B11: 0.3
A12: Number of secondary card charges per split | B12: =B6-1 -> 1.5 | D12: Total cards minus the Lithic card itself
A13: Amount charged per secondary card | B13: =B5/B6 -> 30
A14: Stripe fee per secondary charge | B14: =B13*B10+B11 -> 1.17
A15: TOTAL Stripe fees per split transaction | B15: =B14*B12 -> 1.755 | D15: This is the BIG cost — $0.30 fixed fee per charge adds up fast
A17: Stripe fee for cancelled/uncaptured holds | B17: 0 | D17: Stripe does NOT charge for auth holds that are cancelled before capture
A19: LITHIC FEES — Card Issuing | D19: Source: Lithic Starter program (lithic.com)
A20: Lithic per-card creation fee (virtual) | B20: 0.1
A21: Lithic per-transaction fee (authorization) | B21: 0 | D21: Starter program: no per-auth fee (revenue comes from interchange share)
A22: Cards created per user (one-time) | B22: 1
A23: Lithic card cost amortized per transaction | B23: =B20*B22/50 -> 0.002 | D23: Amortized over 50 transactions per user lifetime
A25: LITHIC INTERCHANGE REVENUE (you earn this)
A26: Interchange share rate (first $100K/mo) | B26: 0.002 | D26: Source: Lithic Starter — 0.2% on first $100K volume
A27: Interchange share rate (above $100K/mo) | B27: 0.004 | D27: Source: Lithic Starter — 0.4% on volume above $100K
A28: Interchange earned per transaction (at 0.2%) | B28: =B5*B26 -> 0.15
A29: Interchange earned per transaction (at 0.4%) | B29: =B5*B27 -> 0.3
A31: OTHER PER-TRANSACTION COSTS
A32: Stripe dispute/chargeback fee (if occurs) | B32: 15 | D32: Source: Stripe — $15 per dispute (refunded if you win)
A33: Estimated dispute rate | B33: 0.005 | D33: Industry avg ~0.5% for card-not-present. Must stay under 1%
A34: Amortized dispute cost per transaction | B34: =B32*B33 -> 0.075
A36: PER-TRANSACTION COST SUMMARY
A37: Total Stripe fees per split | B37: =B15 -> 1.755 | C37: % of txn | D37: =B37/B5 -> 0.0234
A38: Lithic card amortization | B38: =B23 -> 0.002
A39: Amortized dispute cost | B39: =B34 -> 0.075
A40: (-) Interchange revenue earned | B40: =-B28 -> -0.15
A42: NET COST PER SPLIT TRANSACTION | B42: =B37+B38+B39+B40 -> 1.682 | D42: =B42/B5 -> 0.022426667
A44: NET COST PER SPLIT (at 0.4% interchange) | B44: =B37+B38+B39+(-B29) -> 1.532

Sheet Monthly Fixed Costs
A1: SPLITT. — MONTHLY FIXED COSTS
A3: SERVICE | B3: FREE TIER | C3: GROWTH | D3: SCALE | E3: NOTES
A4: Railway (backend hosting) | B4: 5 | C4: 20 | D4: 50 | E4: Hobby $5/mo, Pro $20/mo, usage-based beyond included credit
A5: Supabase (database) | B5: 0 | C5: 25 | D5: 25 | E5: Free: 500MB, 50K MAU. Pro: $25/mo, 100K MAU, 8GB
A6: Vercel (web hosting) | B6: 0 | C6: 20 | D6: 20 | E6: Hobby free (non-commercial!). Pro $20/mo required for commercial use
A7: Resend (email) | B7: 0 | C7: 20 | D7: 90 | E7: Free: 3K emails/mo. Pro: $20/mo for 50K. Scale: $90/mo for 100K
A8: Sentry (error monitoring) | B8: 0 | C8: 26 | D8: 26 | E8: Free: 5K errors/mo. Team: $26/mo for 50K errors
A9: Anthropic Claude API (AI rules) | B9: 5 | C9: 15 | D9: 30 | E9: Haiku is cheap — ~$0.25/1M input tokens. Estimated monthly spend
A10: Domain (paysplitt.com) | B10: 1.5 | C10: 1.5 | D10: 1.5 | E10: ~$18/yr ÷ 12 = $1.50/mo
A11: Expo EAS (mobile builds) | B11: 0 | C11: 0 | D11: 99 | E11: Free builds available. $99/mo for priority builds at scale
A12: UptimeRobot (monitoring) | B12: 0 | C12: 0 | D12: 7 | E12: Free: 50 monitors. Pro: $7/mo
A14: TOTAL MONTHLY FIXED COSTS | B14: =SUM(B4:B12) -> 11.5 | C14: =SUM(C4:C12) -> 127.5 | D14: =SUM(D4:D12) -> 348.5

Sheet Breakeven Analysis
A1: SPLITT. — BREAKEVEN ANALYSIS
A2: How many users / transactions do we need to break even?
A4: SCENARIO | B4: 50 Users | C4: 200 Users | D4: 500 Users | E4: 1,000 Users | F4: 5,000 Users | G4: 10,000 Users
A6: ASSUMPTIONS
A7: Active users | B7: 50 | C7: 200 | D7: 500 | E7: 1000 | F7: 5000 | G7: 10000
A8: Avg splits per user per month | B8: 15 | C8: 15 | D8: 15 | E8: 15 | F8: 15 | G8: 15
A9: Avg transaction amount | B9: ='Per-Transaction Costs'!B5 -> 75 | C9: ='Per-Transaction Costs'!B5 -> 75 | D9: ='Per-Transaction Costs'!B5 -> 75 | E9: ='Per-Transaction Costs'!B5 -> 75 | F9: ='Per-Transaction Costs'!B5 -> 75 | G9: ='Per-Transaction Costs'!B5 -> 75
A10: Avg cards per split | B10: ='Per-Transaction Costs'!B6 -> 2.5 | C10: ='Per-Transaction Costs'!B6 -> 2.5 | D10: ='Per-Transaction Costs'!B6 -> 2.5 | E10: ='Per-Transaction Costs'!B6 -> 2.5 | F10: ='Per-Transaction Costs'!B6 -> 2.5 | G10: ='Per-Transaction Costs'!B6 -> 2.5
A12: MONTHLY VOLUME
A13: Total splits per month | B13: =B7*B8 -> 750 | C13: =C7*C8 -> 3000 | D13: =D7*D8 -> 7500 | E13: =E7*E8 -> 15000 | F13: =F7*F8 -> 75000 | G13: =G7*G8 -> 150000
A14: Total Stripe charges per month | B14: =B13*(B10-1) -> 1125 | C14: =C13*(C10-1) -> 4500 | D14: =D13*(D10-1) -> 11250 | E14: =E13*(E10-1) -> 22500 | F14: =F13*(F10-1) -> 112500 | G14: =G13*(G10-1) -> 225000
A15: Total transaction volume ($) | B15: =B13*B9 -> 56250 | C15: =C13*C9 -> 225000 | D15: =D13*D9 -> 562500 | E15: =E13*E9 -> 1125000 | F15: =F13*F9 -> 5625000 | G15: =G13*G9 -> 11250000
A17: MONTHLY COSTS
A18: Stripe fees (variable) | B18: =B13*'Per-Transaction Costs'!B15 -> 1316.25 | C18: =C13*'Per-Transaction Costs'!B15 -> 5265 | D18: =D13*'Per-Transaction Costs'!B15 -> 13162.5 | E18: =E13*'Per-Transaction Costs'!B15 -> 26325 | F18: =F13*'Per-Transaction Costs'!B15 -> 131625 | G18: =G13*'Per-Transaction Costs'!B15 -> 263250
A19: Dispute costs (estimated) | B19: =B13*'Per-Transaction Costs'!B34 -> 56.25 | C19: =C13*'Per-Transaction Costs'!B34 -> 225 | D19: =D13*'Per-Transaction Costs'!B34 -> 562.5 | E19: =E13*'Per-Transaction Costs'!B34 -> 1125 | F19: =F13*'Per-Transaction Costs'!B34 -> 5625 | G19: =G13*'Per-Transaction Costs'!B34 -> 11250
A20: Fixed infrastructure costs | B20: ='Monthly Fixed Costs'!B14 -> 11.5 | C20: ='Monthly Fixed Costs'!C14 -> 127.5 | D20: ='Monthly Fixed Costs'!C14 -> 127.5 | E20: ='Monthly Fixed Costs'!C14 -> 127.5 | F20: ='Monthly Fixed Costs'!D14 -> 348.5 | G20: ='Monthly Fixed Costs'!D14 -> 348.5
A21: TOTAL MONTHLY COSTS | B21: =B18+B19+B20 -> 1384 | C21: =C18+C19+C20 -> 5617.5 | D21: =D18+D19+D20 -> 13852.5 | E21: =E18+E19+E20 -> 27577.5 | F21: =F18+F19+F20 -> 137598.5 | G21: =G18+G19+G20 -> 274848.5
A23: MONTHLY REVENUE
A24: % users on Free tier | B24: 0.6 | C24: 0.6 | D24: 0.6 | E24: 0.6 | F24: 0.6 | G24: 0.6
A25: % users on Plus ($5/mo) | B25: 0.3 | C25: 0.3 | D25: 0.3 | E25: 0.3 | F25: 0.3 | G25: 0.3
A26: % users on Pro ($10/mo) | B26: 0.1 | C26: 0.1 | D26: 0.1 | E26: 0.1 | F26: 0.1 | G26: 0.1
A27: Subscription revenue | B27: =B7*(B25*5+B26*10) -> 125 | C27: =C7*(C25*5+C26*10) -> 500 | D27: =D7*(D25*5+D26*10) -> 1250 | E27: =E7*(E25*5+E26*10) -> 2500 | F27: =F7*(F25*5+F26*10) -> 12500 | G27: =G7*(G25*5+G26*10) -> 25000
A28: Interchange revenue (Lithic) | B28: =IF(B15<=100000,B15*0.002,100000*0.002+(B15-100000)*0.004) -> 112.5 | C28: =IF(C15<=100000,C15*0.002,100000*0.002+(C15-100000)*0.004) -> 700 | D28: =IF(D15<=100000,D15*0.002,100000*0.002+(D15-100000)*0.004) -> 2050 | E28: =IF(E15<=100000,E15*0.002,100000*0.002+(E15-100000)*0.004) -> 4300 | F28: =IF(F15<=100000,F15*0.002,100000*0.002+(F15-100000)*0.004) -> 22300 | G28: =IF(G15<=100000,G15*0.002,100000*0.002+(G15-100000)*0.004) -> 44800
A29: TOTAL MONTHLY REVENUE | B29: =B27+B28 -> 237.5 | C29: =C27+C28 -> 1200 | D29: =D27+D28 -> 3300 | E29: =E27+E28 -> 6800 | F29: =F27+F28 -> 34800 | G29: =G27+G28 -> 69800
A32: NET MONTHLY PROFIT / (LOSS) | B32: =B29-B21 -> -1146.5 | C32: =C29-C21 -> -4417.5 | D32: =D29-D21 -> -10552.5 | E32: =E29-E21 -> -20777.5 | F32: =F29-F21 -> -102798.5 | G32: =G29-G21 -> -205048.5
A33: Profit margin | B33: =IF(B29=0,0,B32/B29) -> -4.8273684 | C33: =IF(C29=0,0,C32/C29) -> -3.68125 | D33: =IF(D29=0,0,D32/D29) -> -3.1977273 | E33: =IF(E29=0,0,E32/E29) -> -3.0555147 | F33: =IF(F29=0,0,F32/F29) -> -2.9539799 | G33: =IF(G29=0,0,G32/G29) -> -2.9376576
A34: Cost per user per month | B34: =B21/B7 -> 27.68 | C34: =C21/C7 -> 28.0875 | D34: =D21/D7 -> 27.705 | E34: =E21/E7 -> 27.5775 | F34: =F21/F7 -> 27.5197 | G34: =G21/G7 -> 27.48485
A35: Revenue per user per month (ARPU) | B35: =B29/B7 -> 4.75 | C35: =C29/C7 -> 6 | D35: =D29/D7 -> 6.6 | E35: =E29/E7 -> 6.8 | F35: =F29/F7 -> 6.96 | G35: =G29/G7 -> 6.98

Sheet Pricing Strategy
A1: SPLITT. — PRICING STRATEGY & SENSITIVITY
A3: CURRENT PRICING
A4: Free tier — $0/mo | B4: 2 cards, 1 split rule, 30 splits/mo
A5: Plus tier — $5/mo | B5: 5 cards, 3 rules, 5 routing rules, unlimited splits
A6: Pro tier — $10/mo | B6: 10 cards, unlimited rules, analytics, AI routing
A8: THE CORE ECONOMICS PROBLEM
A9: Stripe's $0.30 fixed fee per charge | B9: This is the dominant cost
A10: On a $75 split across 2.5 cards:
A11: Each secondary charge costs | B11: ='Per-Transaction Costs'!B14 -> 1.17
A12: × 1.5 secondary charges
A13: = Total Stripe cost per split | B13: ='Per-Transaction Costs'!B15 -> 1.755
A14: As % of transaction | B14: ='Per-Transaction Costs'!B15/'Per-Transaction Costs'!B5 -> 0.0234
A16: Free user doing 15 splits/mo costs us: | B16: ='Per-Transaction Costs'!B15*15 -> 26.325 | D16: per month — and they pay $0
A17: Plus user doing 15 splits/mo costs us: | B17: ='Per-Transaction Costs'!B15*15 -> 26.325 | C17: they pay $5/mo | D17: =5-B17 -> -21.325
A19: ALTERNATIVE: PER-SPLIT FEE MODEL
A20: Per-split fee charged to user | B20: 0.1 | C20: 0.25 | D20: 0.5
A21: Our cost per split | B21: ='Per-Transaction Costs'!B42 -> 1.682 | C21: ='Per-Transaction Costs'!B42 -> 1.682 | D21: ='Per-Transaction Costs'!B42 -> 1.682
A22: Margin per split | B22: =B20-B21 -> -1.582 | C22: =C20-C21 -> -1.432 | D22: =D20-D21 -> -1.182
A23: Margin % per split | B23: =IF(B20=0,0,B22/B20) -> -15.82 | C23: =IF(C20=0,0,C22/C20) -> -5.728 | D23: =IF(D20=0,0,D22/D20) -> -2.364
A24: Revenue per user/mo (15 splits) | B24: =B20*15 -> 1.5 | C24: =C20*15 -> 3.75 | D24: =D20*15 -> 7.5
A26: RECOMMENDED: HYBRID MODEL
A27: Free: X splits/mo included, then $0.25/split | B27: Limits free tier losses
A28: Free tier included splits/month | B28: 10
A29: Overage fee per split | B29: 0.25
A30: Plus ($5/mo): unlimited splits
A31: Pro ($10/mo): unlimited splits + AI + analytics
A33: MAX LOSS PER FREE USER/MONTH (capped) | B33: ='Per-Transaction Costs'!B42*B28 -> 16.82 | D33: vs unlimited losses with no cap
A35: BREAKEVEN: Plus users need to do X splits to cost $5 | B35: =5/'Per-Transaction Costs'!B42 -> 2.9726516 | D35: splits/mo before Plus subscription covers costs
A37: BREAKEVEN: Pro users need to do X splits to cost $10 | B37: =10/'Per-Transaction Costs'!B42 -> 5.9453032 | D37: splits/mo before Pro subscription covers costs
A39: SENSITIVITY: TRANSACTION SIZE IMPACT | E39: The $0.30 fixed fee hurts more on small transactions
A40: Transaction Amount | B40: Stripe Cost (2 cards) | C40: Cost as % of Txn | D40: Stripe Cost (3 cards) | E40: Cost as % of Txn
A41: 10 | B41: =A41*0.029+0.3 -> 0.59 | C41: =B41/A41 -> 0.059 | D41: =2*(A41/3*0.029+0.3) -> 0.79333333 | E41: =D41/A41 -> 0.079333333
A42: 25 | B42: =A42*0.029+0.3 -> 1.025 | C42: =B42/A42 -> 0.041 | D42: =2*(A42/3*0.029+0.3) -> 1.0833333 | E42: =D42/A42 -> 0.043333333
A43: 50 | B43: =A43*0.029+0.3 -> 1.75 | C43: =B43/A43 -> 0.035 | D43: =2*(A43/3*0.029+0.3) -> 1.5666667 | E43: =D43/A43 -> 0.031333333
A44: 75 | B44: =A44*0.029+0.3 -> 2.475 | C44: =B44/A44 -> 0.033 | D44: =2*(A44/3*0.029+0.3) -> 2.05 | E44: =D44/A44 -> 0.027333333
A45: 100 | B45: =A45*0.029+0.3 -> 3.2 | C45: =B45/A45 -> 0.032 | D45: =2*(A45/3*0.029+0.3) -> 2.5333333 | E45: =D45/A45 -> 0.025333333
A46: 200 | B46: =A46*0.029+0.3 -> 6.1 | C46: =B46/A46 -> 0.0305 | D46: =2*(A46/3*0.029+0.3) -> 4.4666667 | E46: =D46/A46 -> 0.022333333
A47: 500 | B47: =A47*0.029+0.3 -> 14.8 | C47: =B47/A47 -> 0.0296 | D47: =2*(A47/3*0.029+0.3) -> 10.266667 | E47: =D47/A47 -> 0.020533333

Sheet Key Takeaways
A1: SPLITT. — KEY TAKEAWAYS & RECOMMENDATIONS
A3: 1. THE $0.30 PROBLEM
A4: Stripe charges $0.30 per charge regardless of amount. On a $75 split across 2.5 cards, that's ~$0.74 in Stripe fees per split. A free user doing 15 splits/month costs ~$11.10 in Stripe fees alone — and pays nothing.
A6: 2. INTERCHANGE HELPS, BUT ISN'T ENOUGH
A7: Lithic Starter gives you 0.2% on first $100K volume (0.4% above). On $75 that's $0.15 per transaction. Helpful, but covers less than 20% of the Stripe cost.
A9: 3. FREE TIER IS A LOSS LEADER
A10: Every free user costs you $7-11/month in Stripe fees depending on usage. This only works if conversion to paid tiers is strong (>30%).
A12: 4. SUBSCRIPTION ALONE WON'T COVER COSTS
A13: A Plus user ($5/mo) doing 15 splits costs ~$11 in Stripe fees. You lose ~$6/mo on them. Even Pro ($10/mo) loses ~$1/mo at 15 splits. You need either higher prices, per-split fees, or both.
A15: 5. RECOMMENDED: HYBRID PRICING
A16: Cap free tier at 10 splits/month. Charge $0.25 per split after that. Keep Plus at $5/mo and Pro at $10/mo with unlimited splits — the subscription covers the variable cost for moderate users. Heavy users (30+ splits/mo) still lose money on Plus, break even on Pro.
A18: 6. ALTERNATIVE: RAISE SUBSCRIPTION PRICES
... A31: For recurring/predictable splits, ACH is 0.8% capped at $5 per transaction with no fixed fee. This eliminates the $0.30 problem entirely for eligible transactions.
